crumbles/__init__.py
crumbles/py.typed
crumbles-0.1.2.dist-info/LICENSE.txt
crumbles-0.1.2.dist-info/METADATA
crumbles-0.1.2.dist-info/WHEEL
crumbles-0.1.2.dist-info/top_level.txt
crumbles-0.1.2.dist-info/RECORD
