Metadata-Version: 2.2
Name: crumbles
Version: 0.1.2
Summary: A simple library for class based view breadcrumbs for any python web framework
Author-email: Martijn Jacobs <maerteijn@gmail.com>
License: MIT
Project-URL: Repository, https://github.com/maerteijn/crumbles
Classifier: Development Status :: 3 - Alpha
Classifier: Environment :: Console
Classifier: Intended Audience :: Developers
Classifier: Intended Audience :: System Administrators
Classifier: License :: OSI Approved :: MIT License
Classifier: Programming Language :: Python :: 3.10
Classifier: Programming Language :: Python :: 3.11
Classifier: Programming Language :: Python :: 3.12
Classifier: Programming Language :: Python :: 3.13
Classifier: Environment :: Web Environment
Requires-Python: >=3.10
License-File: LICENSE.txt
Provides-Extra: dev
Requires-Dist: pip-tools~=7.3; extra == "dev"
Requires-Dist: ruff~=0.9; extra == "dev"
Requires-Dist: pytest~=7.4; extra == "dev"
Requires-Dist: pytest-cov~=4.0; extra == "dev"
Requires-Dist: mypy~=1.5; extra == "dev"
Requires-Dist: twine~=4.0; extra == "dev"
Provides-Extra: dist
Requires-Dist: build~=1.0; extra == "dist"
